xmz_env/__init__.py
xmz_env/envs/__init__.py
xmz_env/envs/env_xmz.py
xmz_env-0.0.4.dist-info/METADATA
xmz_env-0.0.4.dist-info/WHEEL
xmz_env-0.0.4.dist-info/top_level.txt
xmz_env-0.0.4.dist-info/RECORD
