Metadata-Version: 2.1
Name: xmz-env
Version: 0.0.4
Summary: Fake it until you make it
Home-page: UNKNOWN
License: UNKNOWN
Platform: UNKNOWN
Requires-Dist: gym
